pynt/__init__.py
pynt/_pynt.py
pynt-0.8.2.dist-info/METADATA
pynt-0.8.2.dist-info/RECORD
pynt-0.8.2.dist-info/WHEEL
pynt-0.8.2.dist-info/entry_points.txt
pynt-0.8.2.dist-info/top_level.txt
