Metadata-Version: 1.0
Name: pynt
Version: 0.8.2
Summary: Lightweight Python Build Tool.
Home-page: http://rags.github.com/pynt/
Author: Raghunandan Rao
Author-email: r.raghunandan@gmail.com
License: MIT License
Platform: UNKNOWN
